CHANGES.rst
DESCRIPTION.rst
LICENSE
MANIFEST.in
README.md
setup.py
share/applications/ppp-tray.desktop
share/icons/ppp-tray.png
src/pypulseprofilestray/__init__.py
src/pypulseprofilestray/config.py
src/pypulseprofilestray/icon_dark.png
src/pypulseprofilestray/icon_light.png
src/pypulseprofilestray/tray.py
src/python_pulseaudio_profiles_trayicon.egg-info/PKG-INFO
src/python_pulseaudio_profiles_trayicon.egg-info/SOURCES.txt
src/python_pulseaudio_profiles_trayicon.egg-info/dependency_links.txt
src/python_pulseaudio_profiles_trayicon.egg-info/entry_points.txt
src/python_pulseaudio_profiles_trayicon.egg-info/requires.txt
src/python_pulseaudio_profiles_trayicon.egg-info/top_level.txt