Metadata-Version: 2.1
Name: python-pulseaudio-profiles-trayicon
Version: 0.0.2
Summary: Integrates the python-pulseaudion-profiles library into the system tray icon on Linux.
Home-page: https://github.com/fracpete/python-pulseaudio-profiles-trayicon
Author: Peter "fracpete" Reutemann
Author-email: fracpete@gmail.com
License: MIT License
Platform: UNKNOWN
Classifier: Development Status :: 4 - Beta
Classifier: License :: OSI Approved :: MIT License
Classifier: Topic :: Multimedia :: Sound/Audio
Classifier: Programming Language :: Python :: 3
Classifier: Operating System :: POSIX :: Linux
License-File: LICENSE
